lisa/__init__.py
lisa/_combine_code.py
lisa/config.yaml
lisa/config.yaml.sample
lisa/configure.py
lisa/migrate.py
hyperlisa-2.0.0.dist-info/METADATA
hyperlisa-2.0.0.dist-info/WHEEL
hyperlisa-2.0.0.dist-info/entry_points.txt
hyperlisa-2.0.0.dist-info/top_level.txt
hyperlisa-2.0.0.dist-info/RECORD
