Metadata-Version: 2.4
Name: hyperlisa
Version: 2.0.0
Summary: A package for combining source code files into one
Home-page: https://github.com/moonClimber/hyperlisa
Author: Omar Venturi
Author-email: omar.venturi@hypertrue.com
Classifier: Programming Language :: Python :: 3
Classifier: License :: OSI Approved :: MIT License
Classifier: Operating System :: OS Independent
Requires-Python: >=3.6
Requires-Dist: PyYAML>=5.0
Dynamic: author
Dynamic: author-email
Dynamic: classifier
Dynamic: description
Dynamic: description-content-type
Dynamic: home-page
Dynamic: requires-dist
Dynamic: requires-python
Dynamic: summary
